vibegen/__init__.py
vibegen/vibegen.py
vibegen/config/config.py
vibegen/utils/logger.py
vibegen-1.0.0.dist-info/METADATA
vibegen-1.0.0.dist-info/WHEEL
vibegen-1.0.0.dist-info/licenses/LICENSE
vibegen-1.0.0.dist-info/RECORD
