Metadata-Version: 2.4
Name: vibegen
Version: 1.0.0
Summary: Bring vibes into your code: LLM-powered if-statements and loops!
Project-URL: Homepage, https://github.com/vibe-engineers/vibegen
Project-URL: Issues, https://github.com/vibe-engineers/vibegen/issues
Author-email: vibe-engineers <vibe.engineers.team@gmail.com>, tjtanjin <cjtanjin@gmail.com>, konglyyy <kongleyi99@gmail.com>
License-File: LICENSE
Classifier: License :: OSI Approved :: MIT License
Classifier: Operating System :: OS Independent
Classifier: Programming Language :: Python :: 3
Requires-Python: >=3.0
Requires-Dist: vibetools<2.0.0,>=1.0.0
